Metadata-Version: 1.0
Name: instail
Version: 0.1.2
Summary: A example Python package
Home-page: https://github.com
Author: Nikita Kozhukharov
Author-email: n.korzhikov@gmail.com
License: MIT
Platform: UNKNOWN
